snakemake_executor_plugin_pcluster_slurm/__init__.py
snakemake_executor_plugin_pcluster_slurm/oldinit
snakemake_executor_plugin_pcluster_slurm/utils.py
snakemake_executor_plugin_pcluster_slurm-0.0.31.dist-info/LICENSE
snakemake_executor_plugin_pcluster_slurm-0.0.31.dist-info/METADATA
snakemake_executor_plugin_pcluster_slurm-0.0.31.dist-info/WHEEL
snakemake_executor_plugin_pcluster_slurm-0.0.31.dist-info/RECORD
